connecpy/__init__.py
connecpy/_client_async.py
connecpy/_client_shared.py
connecpy/_client_sync.py
connecpy/_codec.py
connecpy/_compression.py
connecpy/_envelope.py
connecpy/_headers.py
connecpy/_interceptor_async.py
connecpy/_interceptor_sync.py
connecpy/_protocol.py
connecpy/_server_async.py
connecpy/_server_shared.py
connecpy/_server_sync.py
connecpy/_version.py
connecpy/client.py
connecpy/code.py
connecpy/exceptions.py
connecpy/interceptor.py
connecpy/method.py
connecpy/py.typed
connecpy/request.py
connecpy/server.py
connecpy-2.1.0.dist-info/licenses/LICENSE
connecpy-2.1.0.dist-info/WHEEL
connecpy-2.1.0.dist-info/METADATA
connecpy-2.1.0.dist-info/RECORD
