Metadata-Version: 2.4
Name: connecpy
Version: 2.1.0
Summary: Code generator, server library and client library for the Connect Protocol
Author: Connecpy authors
License-File: LICENSE
Requires-Dist: httpx
Requires-Dist: protobuf
Requires-Python: >=3.10
